rcdb/__init__.py
rcdb/__main__.py
rcdb/alias.py
rcdb/app_context.py
rcdb/coda_parser.py
rcdb/condition_query_builder.py
rcdb/config_parser.py
rcdb/constants.py
rcdb/errors.py
rcdb/file_archiver.py
rcdb/halld_daq_config_parser.py
rcdb/lexer.py
rcdb/log_format.py
rcdb/model.py
rcdb/provider.py
rcdb/stopwatch.py
rcdb/update.py
rcdb/version.py
rcdb/cli/__init__.py
rcdb/cli/__main__.py
rcdb/cli/add.py
rcdb/cli/app.py
rcdb/cli/context.py
rcdb/cli/db.py
rcdb/cli/info.py
rcdb/cli/ls.py
rcdb/cli/rp.py
rcdb/cli/run.py
rcdb/cli/select.py
rcdb/cli/web.py
rcdb/cli/repair/__init__.py
rcdb/cli/repair/evio_files.py
rcdb/web/__init__.py
rcdb/web/pagination.py
rcdb/web/run_table.py
rcdb/web/modules/__init__.py
rcdb/web/modules/conditions.py
rcdb/web/modules/files.py
rcdb/web/modules/logs.py
rcdb/web/modules/runs.py
rcdb/web/modules/select_values.py
rcdb/web/modules/statistics.py
rcdb/web/static/favicon.png
rcdb/web/static/humans.txt
rcdb/web/static/robots.txt
rcdb/web/static/style.css
rcdb/web/static/DataTables/datatables.css
rcdb/web/static/DataTables/datatables.js
rcdb/web/static/DataTables/datatables.min.css
rcdb/web/static/DataTables/datatables.min.js
rcdb/web/static/DataTables/DataTables-1.10.10/css/dataTables.bootstrap.css
rcdb/web/static/DataTables/DataTables-1.10.10/css/dataTables.bootstrap.min.css
rcdb/web/static/DataTables/DataTables-1.10.10/css/dataTables.foundation.css
rcdb/web/static/DataTables/DataTables-1.10.10/css/dataTables.foundation.min.css
rcdb/web/static/DataTables/DataTables-1.10.10/css/dataTables.jqueryui.css
rcdb/web/static/DataTables/DataTables-1.10.10/css/dataTables.jqueryui.min.css
rcdb/web/static/DataTables/DataTables-1.10.10/css/jquery.dataTables.css
rcdb/web/static/DataTables/DataTables-1.10.10/css/jquery.dataTables.min.css
rcdb/web/static/DataTables/DataTables-1.10.10/css/jquery.dataTables_themeroller.css
rcdb/web/static/DataTables/DataTables-1.10.10/images/sort_asc.png
rcdb/web/static/DataTables/DataTables-1.10.10/images/sort_asc_disabled.png
rcdb-2.2.10.dist-info/METADATA
rcdb-2.2.10.dist-info/WHEEL
rcdb-2.2.10.dist-info/entry_points.txt
rcdb-2.2.10.dist-info/top_level.txt
rcdb-2.2.10.dist-info/RECORD
