Metadata-Version: 2.4
Name: rcdb
Version: 2.2.10
Summary: RCDB - Run Conditions DataBase
Author-email: Dmitry Romanov <romanov@jlab.org>
License-Expression: MIT
Classifier: Development Status :: 5 - Production/Stable
Classifier: Programming Language :: Python :: 3
Classifier: Programming Language :: Python :: 3.9
Classifier: Programming Language :: Python :: 3.10
Classifier: Programming Language :: Python :: 3.11
Classifier: Programming Language :: Python :: 3.12
Classifier: Programming Language :: Python :: 3.13
Classifier: Programming Language :: Python :: Implementation :: CPython
Classifier: Intended Audience :: Science/Research
Classifier: Intended Audience :: Developers
Classifier: Operating System :: OS Independent
Classifier: Topic :: Scientific/Engineering :: Physics
Classifier: Topic :: Database
Requires-Python: >=3.9
Requires-Dist: markupsafe>=3.0
Requires-Dist: pymysql>=1.1
Requires-Dist: ply>=3.11
Requires-Dist: mako>=1.3
Requires-Dist: click>=8
Requires-Dist: sqlalchemy>=2
Requires-Dist: flask>=3.1.0
Requires-Dist: rich
